<?xml version="1.0" encoding="UTF-8"?>
<vivadoHLSLog:LogRoot xmlns:vivadoHLSLog="www.xilinx.com/vivadoHLSLog">
  <errorLogs>
    <logs>
      <csimLog>
        <logs message="ERROR: [SIM 211-100] 'csim_design' failed: compilation error(s)." projectName="conv" solutionName="solution1" date="2021-03-12T16:47:29.886+0200"/>
        <logs message="ERROR: [SIM 211-100] 'csim_design' failed: compilation error(s)." projectName="conv" solutionName="solution1" date="2021-03-12T16:46:15.658+0200"/>
        <logs message="ERROR: [SIM 211-100] 'csim_design' failed: compilation error(s)." projectName="conv" solutionName="solution1" date="2021-03-12T16:45:23.005+0200"/>
        <logs message="ERROR: [SIM 211-100] 'csim_design' failed: compilation error(s)." projectName="conv" solutionName="solution1" date="2021-03-12T16:44:15.356+0200"/>
      </csimLog>
    </logs>
  </errorLogs>
  <warningLogs>
    <logs>
      <csimLog>
        <logs message="WARNING: [SIM 211-51] HLS only supports CLANG compiler in Linux." projectName="conv" solutionName="solution1" date="2021-03-12T16:49:19.921+0200" type="Warning"/>
        <logs message="WARNING: [SIM 211-51] HLS only supports CLANG compiler in Linux." projectName="conv" solutionName="solution1" date="2021-03-12T16:48:29.213+0200" type="Warning"/>
        <logs message="WARNING: [SIM 211-51] HLS only supports CLANG compiler in Linux." projectName="conv" solutionName="solution1" date="2021-03-12T16:47:08.352+0200" type="Warning"/>
        <logs message="WARNING: [SIM 211-51] HLS only supports CLANG compiler in Linux." projectName="conv" solutionName="solution1" date="2021-03-12T16:46:13.618+0200" type="Warning"/>
        <logs message="WARNING: [SIM 211-51] HLS only supports CLANG compiler in Linux." projectName="conv" solutionName="solution1" date="2021-03-12T16:45:21.175+0200" type="Warning"/>
        <logs message="WARNING: [SIM 211-51] HLS only supports CLANG compiler in Linux." projectName="conv" solutionName="solution1" date="2021-03-12T16:43:51.446+0200" type="Warning"/>
      </csimLog>
    </logs>
  </warningLogs>
</vivadoHLSLog:LogRoot>
